{"pages":[{"id":5310,"book":455,"layout_book":"large_image","created_date":"03-10-2019 15:37","modified_date":"02-10-2021 01:21","content":"","page_number":1,"image":"https://api-vt.umbalena.vn/book/media/?key=eyJhbGciOiJBMjU2S1ciLCJlbmMiOiJBMjU2Q0JDLUhTNTEyIn0.LfIPxedcsMHf96ji6jt9WO3XLU8uvYmKwIbYAcMvk32MJoa5mst-_b7O2CY8MPUwvjUwJRHB46DOGSkYVNVS3sy_OsCXcf_A.CQFSaKCBTZgQbI8BCLFTDQ.JuYK_svJ92kyeiy-5KnqmtA6gVncRe5JBdKv_2DWUMPKFIqM1KPvuRHLnqTcfBre.8Qd8tSQnv5QxZ0zVO-51p6ZuYObF6u3La18GCB46CJw","audio":"https://api-vt.umbalena.vn/book/media/?key=eyJhbGciOiJBMjU2S1ciLCJlbmMiOiJBMjU2Q0JDLUhTNTEyIn0.qDwwEM9C15SOAsa8iJSSm9RAniga-nqINQgQdku57d2BIg2HAlsX23_cgjKEGqnSm99GOJUbuXND_ewPQsgX7XEoPdMm8TMz.PuyeDAUZaOsDfA0uOco8gw.mOJ64cnFwWvQ2MP_XE9l1vgxPCcS1RzS6LGV-AYcDWxjEu81o75yMwRvqCWHDO8s.1s762T9FyhmwVWTfsgF7kH-HCxzU7ld7XhUTiwH3xb8","ar_file":null,"ar_audio":null,"timing_mapping":null,"created_by":108,"modified_by":109},{"id":5311,"book":455,"layout_book":"large_image","created_date":"03-10-2019 15:38","modified_date":"02-10-2021 01:59","content":"Tích| tắc,| tích| tắc\nBác| Đồng Hồ| nhắc:\n“Đã| đến| giờ| rồi\nNgủ thôi| nha| bé!”.","page_number":2,"image":"https://api-vt.umbalena.vn/book/media/?key=eyJhbGciOiJBMjU2S1ciLCJlbmMiOiJBMjU2Q0JDLUhTNTEyIn0.P8xRlwT2zD5CM3OBz6oBQYBqH4BVByatFdiSsIe4HlrioM1dUOIoIIKcMZUAExSTtkoA4Jt7G4BU-ot-JBVLZFwwSIseueV2.GMch4jr7ZA57kQ_yy2cBPg.WOSyeXzBNSh9iwi_EPDXD5Q8UUTCWhguZns_yVAKwV-5iChhN51lvbSW2__mP7tW.CvHiXtEixwDry-dumEFbkyw6MZj8EvOmp34_4eLncZY","audio":"https://api-vt.umbalena.vn/book/media/?key=eyJhbGciOiJBMjU2S1ciLCJlbmMiOiJBMjU2Q0JDLUhTNTEyIn0.zJ0EIybWqEi6MPzV6opt93q-I1XyrExg2ai2JoWnGFq75jWgCG5exIxytoXJiwuCi1mhcEXHRzmuH-62F0OrHKntpleYCoRo.Dkoj0h8JJr9LtySgoxVjJQ.j8jj9FnqBtC-MXRCJ8e0K6Ke9ar3gX1fPeCPKAkjWvX3y_huF1erTU6TaTUg7BSa.bPPwkhuLZf_3F_4RnTLiIqtxt7MFtyvzt7esDCt5jgg","ar_file":null,"ar_audio":null,"timing_mapping":"{\n \"fragments\": [\n  {\n   \"begin\": \"0.000\", \n   \"children\": [], \n   \"end\": \"0.320\", \n   \"id\": \"f000001\", \n   \"language\": \"vie\", \n   \"lines\": [\n    \"T\\u00edch\"\n   ]\n  }, \n  {\n   \"begin\": \"0.320\", \n   \"children\": [], \n   \"end\": \"1.160\", \n   \"id\": \"f000002\", \n   \"language\": \"vie\", \n   \"lines\": [\n    \"t\\u1eafc,\"\n   ]\n  }, \n  {\n   \"begin\": \"1.160\", \n   \"children\": [], \n   \"end\": \"1.440\", \n   \"id\": \"f000003\", \n   \"language\": \"vie\", \n   \"lines\": [\n    \"t\\u00edch\"\n   ]\n  }, \n  {\n   \"begin\": \"1.440\", \n   \"children\": [], \n   \"end\": \"2.440\", \n   \"id\": \"f000004\", \n   \"language\": \"vie\", \n   \"lines\": [\n    \"t\\u1eafc\"\n   ]\n  }, \n  {\n   \"begin\": \"2.440\", \n   \"children\": [], \n   \"end\": \"2.800\", \n   \"id\": \"f000005\", \n   \"language\": \"vie\", \n   \"lines\": [\n    \"** B\\u00e1c\"\n   ]\n  }, \n  {\n   \"begin\": \"2.800\", \n   \"children\": [], \n   \"end\": \"3.400\", \n   \"id\": \"f000006\", \n   \"language\": \"vie\", \n   \"lines\": [\n    \"\\u0110\\u1ed3ng H\\u1ed3\"\n   ]\n  }, \n  {\n   \"begin\": \"3.400\", \n   \"children\": [], \n   \"end\": \"3.600\", \n   \"id\": \"f000007\", \n   \"language\": \"vie\", \n   \"lines\": [\n    \"nh\\u1eafc:\"\n   ]\n  }, \n  {\n   \"begin\": \"3.600\", \n   \"children\": [], \n   \"end\": \"4.720\", \n   \"id\": \"f000008\", \n   \"language\": \"vie\", \n   \"lines\": [\n    \"** \\u201c\\u0110\\u00e3\"\n   ]\n  }, \n  {\n   \"begin\": \"4.720\", \n   \"children\": [], \n   \"end\": \"5.000\", \n   \"id\": \"f000009\", \n   \"language\": \"vie\", \n   \"lines\": [\n    \"\\u0111\\u1ebfn\"\n   ]\n  }, \n  {\n   \"begin\": \"5.000\", \n   \"children\": [], \n   \"end\": \"5.360\", \n   \"id\": \"f000010\", \n   \"language\": \"vie\", \n   \"lines\": [\n    \"gi\\u1edd\"\n   ]\n  }, \n  {\n   \"begin\": \"5.360\", \n   \"children\": [], \n   \"end\": \"6.400\", \n   \"id\": \"f000011\", \n   \"language\": \"vie\", \n   \"lines\": [\n    \"r\\u1ed3i\"\n   ]\n  }, \n  {\n   \"begin\": \"6.400\", \n   \"children\": [], \n   \"end\": \"7.160\", \n   \"id\": \"f000012\", \n   \"language\": \"vie\", \n   \"lines\": [\n    \"** Ng\\u1ee7 th\\u00f4i\"\n   ]\n  }, \n  {\n   \"begin\": \"7.160\", \n   \"children\": [], \n   \"end\": \"7.480\", \n   \"id\": \"f000013\", \n   \"language\": \"vie\", \n   \"lines\": [\n    \"nha\"\n   ]\n  }, \n  {\n   \"begin\": \"7.480\", \n   \"children\": [], \n   \"end\": \"8.200\", \n   \"id\": \"f000014\", \n   \"language\": \"vie\", \n   \"lines\": [\n    \"be\\u0301!\\u201d.\"\n   ]\n  }\n ]\n}","created_by":108,"modified_by":109},{"id":5312,"book":455,"layout_book":"large_image","created_date":"03-10-2019 15:38","modified_date":"02-10-2021 07:52","content":"Mắt bé| ríu lại\nMiệng| ngáp| thật lâu\nBạn| nào| mau mau\nTheo| bé| đi ngủ?","page_number":3,"image":"https://api-vt.umbalena.vn/book/media/?key=eyJhbGciOiJBMjU2S1ciLCJlbmMiOiJBMjU2Q0JDLUhTNTEyIn0.iK_uBhIf_Ul5jaVOI75EQYGvlLCiRQ2rlrjIC6NkE7gJrH9KWISrAIWJtNvWEXXUTMI9Q1UgmrfZNXeILbopl7Jwp1-CJ-AP.ZZWVsFLoNnl-1y65bQn-cQ.mMk9QWP8d0lnCDTzrJqfE4nQqNNvxllA_ipzSz2mNBLbb_KNR6nBmwLd5TjImxSv.Vgo-KyL5BnXoZ-7O0SEYi8ipwNEo3G_ddldI65v0WPw","audio":"https://api-vt.umbalena.vn/book/media/?key=eyJhbGciOiJBMjU2S1ciLCJlbmMiOiJBMjU2Q0JDLUhTNTEyIn0.oduM-Pfcsl8jP1f_cGc_apR06wbveQ2xw_0ePh1U5SU8Cqr16WAHYqIvI0qF2rP4ZJIuAi1673tFzsr_NamHdw8UocV51Upj.VX3FAg74S1RBg_qorCsuhw.dIEPJcdjGvDb-I9AX9RKdDCCNrZ1NM-3DS8obX3nI0RUr3Z9X-olevODG34zDlYU.wmrQHp8vsNwrhRL1tCg6kIi1iQE2CGbmhvHzqOjUkIw","ar_file":null,"ar_audio":null,"timing_mapping":"{\n \"fragments\": [\n  {\n   \"begin\": \"0.000\", \n   \"children\": [], \n   \"end\": \"0.560\", \n   \"id\": \"f000001\", \n   \"language\": \"vie\", \n   \"lines\": [\n    \"M\\u1eaft b\\u00e9\"\n   ]\n  }, \n  {\n   \"begin\": \"0.560\", \n   \"children\": [], \n   \"end\": \"1.400\", \n   \"id\": \"f000002\", \n   \"language\": \"vie\", \n   \"lines\": [\n    \"r\\u00edu l\\u1ea1i\"\n   ]\n  }, \n  {\n   \"begin\": \"1.400\", \n   \"children\": [], \n   \"end\": \"2.680\", \n   \"id\": \"f000003\", \n   \"language\": \"vie\", \n   \"lines\": [\n    \"** Mi\\u1ec7ng\"\n   ]\n  }, \n  {\n   \"begin\": \"2.680\", \n   \"children\": [], \n   \"end\": \"3.080\", \n   \"id\": \"f000004\", \n   \"language\": \"vie\", \n   \"lines\": [\n    \"ng\\u00e1p\"\n   ]\n  }, \n  {\n   \"begin\": \"3.080\", \n   \"children\": [], \n   \"end\": \"4.760\", \n   \"id\": \"f000005\", \n   \"language\": \"vie\", \n   \"lines\": [\n    \"th\\u1eadt l\\u00e2u\"\n   ]\n  }, \n  {\n   \"begin\": \"4.760\", \n   \"children\": [], \n   \"end\": \"5.040\", \n   \"id\": \"f000006\", \n   \"language\": \"vie\", \n   \"lines\": [\n    \"** B\\u1ea1n\"\n   ]\n  }, \n  {\n   \"begin\": \"5.040\", \n   \"children\": [], \n   \"end\": \"5.480\", \n   \"id\": \"f000007\", \n   \"language\": \"vie\", \n   \"lines\": [\n    \"n\\u00e0o\"\n   ]\n  }, \n  {\n   \"begin\": \"5.480\", \n   \"children\": [], \n   \"end\": \"6.760\", \n   \"id\": \"f000008\", \n   \"language\": \"vie\", \n   \"lines\": [\n    \"mau mau\"\n   ]\n  }, \n  {\n   \"begin\": \"6.760\", \n   \"children\": [], \n   \"end\": \"7.120\", \n   \"id\": \"f000009\", \n   \"language\": \"vie\", \n   \"lines\": [\n    \"** Theo\"\n   ]\n  }, \n  {\n   \"begin\": \"7.120\", \n   \"children\": [], \n   \"end\": \"7.480\", \n   \"id\": \"f000010\", \n   \"language\": \"vie\", \n   \"lines\": [\n    \"b\\u00e9\"\n   ]\n  }, \n  {\n   \"begin\": \"7.480\", \n   \"children\": [], \n   \"end\": \"8.320\", \n   \"id\": \"f000011\", \n   \"language\": \"vie\", \n   \"lines\": [\n    \"\\u0111i ng\\u1ee7?\"\n   ]\n  }\n ]\n}","created_by":108,"modified_by":109},{"id":5313,"book":455,"layout_book":"large_image","created_date":"03-10-2019 15:38","modified_date":"02-10-2021 07:53","content":"Bộ| đồ ngủ| này\nXinh xắn| biết bao\nBé| ơi| mặc vào\nTrước| khi| đi ngủ.","page_number":4,"image":"https://api-vt.umbalena.vn/book/media/?key=eyJhbGciOiJBMjU2S1ciLCJlbmMiOiJBMjU2Q0JDLUhTNTEyIn0.Wtyv5hEI5HDtDsxMJJ95KGP28sQyJgd1a8-dPoXokdrWRV-wiDxdBEYIwT33UDKyOsdwy6OuIBdJdP7moANXVLv05Jx5OOCh.u6NbBCoWNotMFRI1hvIUyA.bUrgCxOW3xLVIflRB4LlWg6kwJyz3sxRWuiWlhfCo6Gt8ffArZKxel2NJDSx8cdA.eBCWIO2j1ONTJ5mdAc366bDQpeRDnVjxBmbXZCG_D0c","audio":"https://api-vt.umbalena.vn/book/media/?key=eyJhbGciOiJBMjU2S1ciLCJlbmMiOiJBMjU2Q0JDLUhTNTEyIn0.Bk_6Jy4wVey6X1m4T4u78laT-hRlM5wfpEvFWkSH3fadV-Rbch57jbLYgnXCiRla1ZKYEstX4H6fqtH61XNN4yT4eWD1F6je.YIRgPUOiRsXkoYMnPSnhGA.jh9UGPTTesmtqRNB4zIazudDVNHp-xRDkSqlWvWHuxyps0aaLfoAGZtFZ8MAQnBx.HEz_bFBbc-bBehoL9EKxNzRrssg2xh9vI5izcIofcGo","ar_file":null,"ar_audio":null,"timing_mapping":"{\n \"fragments\": [\n  {\n   \"begin\": \"0.000\", \n   \"children\": [], \n   \"end\": \"0.480\", \n   \"id\": \"f000001\", \n   \"language\": \"vie\", \n   \"lines\": [\n    \"B\\u00f4\\u0323\"\n   ]\n  }, \n  {\n   \"begin\": \"0.480\", \n   \"children\": [], \n   \"end\": \"1.120\", \n   \"id\": \"f000002\", \n   \"language\": \"vie\", \n   \"lines\": [\n    \"\\u0111\\u00f4\\u0300 ngu\\u0309\"\n   ]\n  }, \n  {\n   \"begin\": \"1.120\", \n   \"children\": [], \n   \"end\": \"1.960\", \n   \"id\": \"f000003\", \n   \"language\": \"vie\", \n   \"lines\": [\n    \"na\\u0300y\"\n   ]\n  }, \n  {\n   \"begin\": \"1.960\", \n   \"children\": [], \n   \"end\": \"2.760\", \n   \"id\": \"f000004\", \n   \"language\": \"vie\", \n   \"lines\": [\n    \"** Xinh x\\u1eafn\"\n   ]\n  }, \n  {\n   \"begin\": \"2.760\", \n   \"children\": [], \n   \"end\": \"4.120\", \n   \"id\": \"f000005\", \n   \"language\": \"vie\", \n   \"lines\": [\n    \"bi\\u1ebft bao\"\n   ]\n  }, \n  {\n   \"begin\": \"4.120\", \n   \"children\": [], \n   \"end\": \"4.520\", \n   \"id\": \"f000006\", \n   \"language\": \"vie\", \n   \"lines\": [\n    \"** B\\u00e9\"\n   ]\n  }, \n  {\n   \"begin\": \"4.520\", \n   \"children\": [], \n   \"end\": \"4.840\", \n   \"id\": \"f000007\", \n   \"language\": \"vie\", \n   \"lines\": [\n    \"\\u01a1i\"\n   ]\n  }, \n  {\n   \"begin\": \"4.840\", \n   \"children\": [], \n   \"end\": \"6.040\", \n   \"id\": \"f000008\", \n   \"language\": \"vie\", \n   \"lines\": [\n    \"m\\u1eb7c v\\u00e0o\"\n   ]\n  }, \n  {\n   \"begin\": \"6.040\", \n   \"children\": [], \n   \"end\": \"6.360\", \n   \"id\": \"f000009\", \n   \"language\": \"vie\", \n   \"lines\": [\n    \"** Tr\\u01b0\\u1edbc\"\n   ]\n  }, \n  {\n   \"begin\": \"6.360\", \n   \"children\": [], \n   \"end\": \"6.800\", \n   \"id\": \"f000010\", \n   \"language\": \"vie\", \n   \"lines\": [\n    \"khi\"\n   ]\n  }, \n  {\n   \"begin\": \"6.800\", \n   \"children\": [], \n   \"end\": \"7.680\", \n   \"id\": \"f000011\", \n   \"language\": \"vie\", \n   \"lines\": [\n    \"\\u0111i ng\\u1ee7.\"\n   ]\n  }\n ]\n}","created_by":108,"modified_by":109},{"id":5314,"book":455,"layout_book":"large_image","created_date":"03-10-2019 15:39","modified_date":"02-10-2021 07:54","content":"Chiếc giường| vững chãi\nThêm| cái nệm| êm\nBé nằm| mỗi đêm\nĐể say| giấc ngủ.","page_number":5,"image":"https://api-vt.umbalena.vn/book/media/?key=eyJhbGciOiJBMjU2S1ciLCJlbmMiOiJBMjU2Q0JDLUhTNTEyIn0.yTTzGKmyf5JkuwC_a_euEHiwxxQDB4cg5O5giK3KlgHne2HAl0GoiPnAAokh-D8jRuEwsLVTYkRHebGfN3Bngi6uPY6H771-.OgrAKf_iyWClxAaLDZDdkA.z4FQHESVXDb_aVMb397_kl7shftg6TtgYRYn86b7AAcdu6j9s0kI1Sv1zE1q8XEZ.LH1n5tzCRg-FcGcqTzskIuKYopkt8azSANv3ya2sXdM","audio":"https://api-vt.umbalena.vn/book/media/?key=eyJhbGciOiJBMjU2S1ciLCJlbmMiOiJBMjU2Q0JDLUhTNTEyIn0.bikKVT49SmzulbW9K8YXmHCS_ya3gH2_Db1Kmv3FO129w1o5peRX74WJnxna9MILwXg9mTTVhHqqZmajC90Vs3R3P63SRLGD.31Id5Xc0bhzabmu-CKyeuA.9x47CeIFsU7Cg0B0hb0PUjjka9e1YKJ9biFVxB9VJ0ggSZgmhq9DOmgG16Vjuz5Q.U0TR1EQVe2HLVq0wlamKICE5f5oGn4nxTau_SqkGjqw","ar_file":null,"ar_audio":null,"timing_mapping":"{\n \"fragments\": [\n  {\n   \"begin\": \"0.000\", \n   \"children\": [], \n   \"end\": \"1.000\", \n   \"id\": \"f000001\", \n   \"language\": \"vie\", \n   \"lines\": [\n    \"Chi\\u1ebfc gi\\u01b0\\u1eddng\"\n   ]\n  }, \n  {\n   \"begin\": \"1.000\", \n   \"children\": [], \n   \"end\": \"2.320\", \n   \"id\": \"f000002\", \n   \"language\": \"vie\", \n   \"lines\": [\n    \"v\\u1eefng ch\\u00e3i\"\n   ]\n  }, \n  {\n   \"begin\": \"2.320\", \n   \"children\": [], \n   \"end\": \"2.720\", \n   \"id\": \"f000003\", \n   \"language\": \"vie\", \n   \"lines\": [\n    \"** Th\\u00eam\"\n   ]\n  }, \n  {\n   \"begin\": \"2.720\", \n   \"children\": [], \n   \"end\": \"3.400\", \n   \"id\": \"f000004\", \n   \"language\": \"vie\", \n   \"lines\": [\n    \"ca\\u0301i n\\u00ea\\u0323m\"\n   ]\n  }, \n  {\n   \"begin\": \"3.400\", \n   \"children\": [], \n   \"end\": \"4.400\", \n   \"id\": \"f000005\", \n   \"language\": \"vie\", \n   \"lines\": [\n    \"\\u00eam\"\n   ]\n  }, \n  {\n   \"begin\": \"4.400\", \n   \"children\": [], \n   \"end\": \"5.360\", \n   \"id\": \"f000006\", \n   \"language\": \"vie\", \n   \"lines\": [\n    \"** B\\u00e9 n\\u1eb1m\"\n   ]\n  }, \n  {\n   \"begin\": \"5.360\", \n   \"children\": [], \n   \"end\": \"6.240\", \n   \"id\": \"f000007\", \n   \"language\": \"vie\", \n   \"lines\": [\n    \"m\\u1ed7i \\u0111\\u00eam\"\n   ]\n  }, \n  {\n   \"begin\": \"6.240\", \n   \"children\": [], \n   \"end\": \"7.080\", \n   \"id\": \"f000008\", \n   \"language\": \"vie\", \n   \"lines\": [\n    \"** \\u0110\\u00ea\\u0309 say\"\n   ]\n  }, \n  {\n   \"begin\": \"7.080\", \n   \"children\": [], \n   \"end\": \"7.920\", \n   \"id\": \"f000009\", \n   \"language\": \"vie\", \n   \"lines\": [\n    \"gi\\u00e2\\u0301c ngu\\u0309.\"\n   ]\n  }\n ]\n}","created_by":108,"modified_by":109},{"id":5315,"book":455,"layout_book":"large_image","created_date":"03-10-2019 15:39","modified_date":"02-10-2021 08:18","content":"Chiếc gối| mềm mại\nVuông vức,| xinh xinh\nGiúp| cho| chúng mình\nGối| đầu| ngon giấc.","page_number":6,"image":"https://api-vt.umbalena.vn/book/media/?key=eyJhbGciOiJBMjU2S1ciLCJlbmMiOiJBMjU2Q0JDLUhTNTEyIn0.KspXLON7SGNtpD5N-5z7gutRlb0EiaFeZea9M94V3prrwZTG5h80xonPBBJPtjSpmapxQ6DkMA323TuAjiQy8DXv3u8JDSDn.BXdIoVH7S683M0CusGprDQ.KMWoeB9M2JMrRyfHmhssFYrqMVjO2UAtZAF9fHYoS54BlJ7jrXIVtNu29RfiFEqg.-B8arJIxe3q6YynoqoEcwS47AuAGLUbuVpYs2vcqEkc","audio":"https://api-vt.umbalena.vn/book/media/?key=eyJhbGciOiJBMjU2S1ciLCJlbmMiOiJBMjU2Q0JDLUhTNTEyIn0.bJmcdksDZRDPI0Rn_K6g7MM7KjomNlvg5RA7CgqKuZvm7uYKzCsAaqkFt1vZmlvrQDohxbWZDQoBhFshFUZvCc6U0AqqbGJ5.cHYVXOMDUfMfVSzOiFRbwg.h-DnfEG-2JWN8y_Q-XO9QlO3je2pi_5NNq-P5vo1AwZmOGD1TJIvv63977V1dvAL.lsJnTzZVw0sKItG1cuApcnxvGuHlZyhIsPbBsR-c0IQ","ar_file":null,"ar_audio":null,"timing_mapping":"{\n \"fragments\": [\n  {\n   \"begin\": \"0.000\", \n   \"children\": [], \n   \"end\": \"1.200\", \n   \"id\": \"f000001\", \n   \"language\": \"vie\", \n   \"lines\": [\n    \"Chi\\u1ebfc g\\u1ed1i\"\n   ]\n  }, \n  {\n   \"begin\": \"1.200\", \n   \"children\": [], \n   \"end\": \"2.320\", \n   \"id\": \"f000002\", \n   \"language\": \"vie\", \n   \"lines\": [\n    \"m\\u1ec1m m\\u1ea1i\"\n   ]\n  }, \n  {\n   \"begin\": \"2.320\", \n   \"children\": [], \n   \"end\": \"3.000\", \n   \"id\": \"f000003\", \n   \"language\": \"vie\", \n   \"lines\": [\n    \"** Vu\\u00f4ng v\\u1ee9c,\"\n   ]\n  }, \n  {\n   \"begin\": \"3.000\", \n   \"children\": [], \n   \"end\": \"4.520\", \n   \"id\": \"f000004\", \n   \"language\": \"vie\", \n   \"lines\": [\n    \"xinh xinh\"\n   ]\n  }, \n  {\n   \"begin\": \"4.520\", \n   \"children\": [], \n   \"end\": \"4.920\", \n   \"id\": \"f000005\", \n   \"language\": \"vie\", \n   \"lines\": [\n    \"** Giu\\u0301p\"\n   ]\n  }, \n  {\n   \"begin\": \"4.920\", \n   \"children\": [], \n   \"end\": \"5.320\", \n   \"id\": \"f000006\", \n   \"language\": \"vie\", \n   \"lines\": [\n    \"cho\"\n   ]\n  }, \n  {\n   \"begin\": \"5.320\", \n   \"children\": [], \n   \"end\": \"6.520\", \n   \"id\": \"f000007\", \n   \"language\": \"vie\", \n   \"lines\": [\n    \"ch\\u00fang m\\u00ecnh\"\n   ]\n  }, \n  {\n   \"begin\": \"6.520\", \n   \"children\": [], \n   \"end\": \"6.920\", \n   \"id\": \"f000008\", \n   \"language\": \"vie\", \n   \"lines\": [\n    \"** G\\u1ed1i\"\n   ]\n  }, \n  {\n   \"begin\": \"6.920\", \n   \"children\": [], \n   \"end\": \"7.240\", \n   \"id\": \"f000009\", \n   \"language\": \"vie\", \n   \"lines\": [\n    \"\\u0111\\u1ea7u\"\n   ]\n  }, \n  {\n   \"begin\": \"7.240\", \n   \"children\": [], \n   \"end\": \"8.200\", \n   \"id\": \"f000010\", \n   \"language\": \"vie\", \n   \"lines\": [\n    \"ngon gi\\u1ea5c.\"\n   ]\n  }\n ]\n}","created_by":108,"modified_by":109},{"id":5316,"book":455,"layout_book":"large_image","created_date":"03-10-2019 15:39","modified_date":"02-10-2021 05:03","content":"Bạn| gấu bông| nhé\nNgộ nghĩnh,| đáng yêu\nBé| thương| thật nhiều\nÔm| bạn| mỗi tối.","page_number":7,"image":"https://api-vt.umbalena.vn/book/media/?key=eyJhbGciOiJBMjU2S1ciLCJlbmMiOiJBMjU2Q0JDLUhTNTEyIn0.qzNLktCjp2DVBNsb9ZIn3DX4JMX8XCHnhY3LfvWSB48pWg2X2w_LDhlrm4Lz1jzBItKyMmWHtRTqOrKaLiltOPjwtKxmfvYF.o3q2ULIozyAaz5sGs9WaNw.jgGIPuE-0sUiHOI2or3sQxrBxMQ1qtUaRDAAQbRg_emEBhvYkMjbuxct5tk-4Ri5.mk3DILcumFs7EMvsvNQl0C4zDBQnTfK1HNKr-Y3MeTA","audio":"https://api-vt.umbalena.vn/book/media/?key=eyJhbGciOiJBMjU2S1ciLCJlbmMiOiJBMjU2Q0JDLUhTNTEyIn0.cchNDOx-hVxEP3qZlRzvpAIsGzhRceuYqW35EeLsIhghLcrLs6oohibtHQW8OZzBVoWfDXoSvvVNpp2yitzWdGLb6T_xE2Q2.XlE6BFspO1V8Apa4GQRooA.ZuUQA3bCz1AO8uuxWdWz-paL11UjhRceS02gzBvPsGN0YEZWelUWO4omqJ6LLyle.CUCloRBKFIS2a1_s4T7D6NkVZHFgYKxUhVy7LyYAmPs","ar_file":null,"ar_audio":null,"timing_mapping":"{\n \"fragments\": [\n  {\n   \"begin\": \"0.000\", \n   \"children\": [], \n   \"end\": \"0.760\", \n   \"id\": \"f000001\", \n   \"language\": \"vie\", \n   \"lines\": [\n    \"B\\u1ea1n\"\n   ]\n  }, \n  {\n   \"begin\": \"0.760\", \n   \"children\": [], \n   \"end\": \"1.400\", \n   \"id\": \"f000002\", \n   \"language\": \"vie\", \n   \"lines\": [\n    \"g\\u1ea5u b\\u00f4ng\"\n   ]\n  }, \n  {\n   \"begin\": \"1.400\", \n   \"children\": [], \n   \"end\": \"2.320\", \n   \"id\": \"f000003\", \n   \"language\": \"vie\", \n   \"lines\": [\n    \"nh\\u00e9\"\n   ]\n  }, \n  {\n   \"begin\": \"2.320\", \n   \"children\": [], \n   \"end\": \"3.120\", \n   \"id\": \"f000004\", \n   \"language\": \"vie\", \n   \"lines\": [\n    \"** Ng\\u1ed9 ngh\\u0129nh,\"\n   ]\n  }, \n  {\n   \"begin\": \"3.120\", \n   \"children\": [], \n   \"end\": \"4.480\", \n   \"id\": \"f000005\", \n   \"language\": \"vie\", \n   \"lines\": [\n    \"\\u0111\\u00e1ng y\\u00eau\"\n   ]\n  }, \n  {\n   \"begin\": \"4.480\", \n   \"children\": [], \n   \"end\": \"4.800\", \n   \"id\": \"f000006\", \n   \"language\": \"vie\", \n   \"lines\": [\n    \"** B\\u00e9\"\n   ]\n  }, \n  {\n   \"begin\": \"4.800\", \n   \"children\": [], \n   \"end\": \"5.160\", \n   \"id\": \"f000007\", \n   \"language\": \"vie\", \n   \"lines\": [\n    \"th\\u01b0\\u01a1ng\"\n   ]\n  }, \n  {\n   \"begin\": \"5.160\", \n   \"children\": [], \n   \"end\": \"6.520\", \n   \"id\": \"f000008\", \n   \"language\": \"vie\", \n   \"lines\": [\n    \"th\\u1eadt nhi\\u1ec1u\"\n   ]\n  }, \n  {\n   \"begin\": \"6.520\", \n   \"children\": [], \n   \"end\": \"6.720\", \n   \"id\": \"f000009\", \n   \"language\": \"vie\", \n   \"lines\": [\n    \"** \\u00d4m\"\n   ]\n  }, \n  {\n   \"begin\": \"6.720\", \n   \"children\": [], \n   \"end\": \"7.480\", \n   \"id\": \"f000010\", \n   \"language\": \"vie\", \n   \"lines\": [\n    \"b\\u1ea1n\"\n   ]\n  }, \n  {\n   \"begin\": \"7.480\", \n   \"children\": [], \n   \"end\": \"8.360\", \n   \"id\": \"f000011\", \n   \"language\": \"vie\", \n   \"lines\": [\n    \"m\\u1ed7i t\\u1ed1i.\"\n   ]\n  }\n ]\n}","created_by":108,"modified_by":109},{"id":5317,"book":455,"layout_book":"large_image","created_date":"03-10-2019 15:39","modified_date":"02-10-2021 07:54","content":"Thêm| cái| chăn ấm|\nVừa mềm| vừa to\nBé| chẳng cần| lo\nMùa đông| bị lạnh.","page_number":8,"image":"https://api-vt.umbalena.vn/book/media/?key=eyJhbGciOiJBMjU2S1ciLCJlbmMiOiJBMjU2Q0JDLUhTNTEyIn0.2fHyT6iz5x53etUkmFX5EU3wOujV0gdpd4tpRXye35pyVvdOyOog_xgTIGvgUw0vLPGcnAaje5g_KlG6ip8rXDNleP8QGaQ9.LzgZVy97pT1_0FsrmlFWLQ.VjS1SdIdj-iTgWTnRvG2P_2cqM3svXtKRYf2UPafv_cS5ddp_RaixwcPZFoNsh1h.6149DV-qPCKWNyVYKkMioFo40jtezf6aLzlwzIpBOfU","audio":"https://api-vt.umbalena.vn/book/media/?key=eyJhbGciOiJBMjU2S1ciLCJlbmMiOiJBMjU2Q0JDLUhTNTEyIn0.eWzeWAS42olRbw5Qy6AlgKqWiiN9w_NLMlth718UUB9xoPaLilzPvrnNThrUnBqIwxYBcwygMEkWg9pfN27hCoiYXuQKt-lA.lneAa_NbhRrxI-0knlqgbA.GifWjwT0JHCt6mqoIsoiWgRz4pfp3VYFgD4n5Amymhp_YVmYZNIR3dx5mRHgSiwy.yjxPZpiOPdxzWkBu3khFb9gmoI1on0YYgcTy0EUbq2I","ar_file":null,"ar_audio":null,"timing_mapping":"{\n \"fragments\": [\n  {\n   \"begin\": \"0.000\", \n   \"children\": [], \n   \"end\": \"0.800\", \n   \"id\": \"f000001\", \n   \"language\": \"vie\", \n   \"lines\": [\n    \"Th\\u00eam\"\n   ]\n  }, \n  {\n   \"begin\": \"0.800\", \n   \"children\": [], \n   \"end\": \"1.280\", \n   \"id\": \"f000002\", \n   \"language\": \"vie\", \n   \"lines\": [\n    \"ca\\u0301i\"\n   ]\n  }, \n  {\n   \"begin\": \"1.280\", \n   \"children\": [], \n   \"end\": \"1.760\", \n   \"id\": \"f000003\", \n   \"language\": \"vie\", \n   \"lines\": [\n    \"ch\\u0103n \\u00e2\\u0301m\"\n   ]\n  }, \n  {\n   \"begin\": \"1.760\", \n   \"children\": [], \n   \"end\": \"2.400\", \n   \"id\": \"f000004\", \n   \"language\": \"vie\", \n   \"lines\": [\n    \"\"\n   ]\n  }, \n  {\n   \"begin\": \"2.400\", \n   \"children\": [], \n   \"end\": \"3.200\", \n   \"id\": \"f000005\", \n   \"language\": \"vie\", \n   \"lines\": [\n    \"** V\\u1eeba m\\u1ec1m\"\n   ]\n  }, \n  {\n   \"begin\": \"3.200\", \n   \"children\": [], \n   \"end\": \"4.880\", \n   \"id\": \"f000006\", \n   \"language\": \"vie\", \n   \"lines\": [\n    \"v\\u1eeba to\"\n   ]\n  }, \n  {\n   \"begin\": \"4.880\", \n   \"children\": [], \n   \"end\": \"5.200\", \n   \"id\": \"f000007\", \n   \"language\": \"vie\", \n   \"lines\": [\n    \"** B\\u00e9\"\n   ]\n  }, \n  {\n   \"begin\": \"5.200\", \n   \"children\": [], \n   \"end\": \"6.800\", \n   \"id\": \"f000008\", \n   \"language\": \"vie\", \n   \"lines\": [\n    \"ch\\u1eb3ng c\\u1ea7n\"\n   ]\n  }, \n  {\n   \"begin\": \"6.800\", \n   \"children\": [], \n   \"end\": \"7.120\", \n   \"id\": \"f000009\", \n   \"language\": \"vie\", \n   \"lines\": [\n    \"lo\"\n   ]\n  }, \n  {\n   \"begin\": \"7.120\", \n   \"children\": [], \n   \"end\": \"7.480\", \n   \"id\": \"f000010\", \n   \"language\": \"vie\", \n   \"lines\": [\n    \"** M\\u00f9a \\u0111\\u00f4ng\"\n   ]\n  }, \n  {\n   \"begin\": \"7.480\", \n   \"children\": [], \n   \"end\": \"8.520\", \n   \"id\": \"f000011\", \n   \"language\": \"vie\", \n   \"lines\": [\n    \"b\\u1ecb l\\u1ea1nh.\"\n   ]\n  }\n ]\n}","created_by":108,"modified_by":109},{"id":5318,"book":455,"layout_book":"large_image","created_date":"03-10-2019 15:39","modified_date":"02-10-2021 05:01","content":"Ồ| chiếc đèn| ngủ|\nLung linh| ánh vàng\nCho| bé| mơ màng\nChìm vào| giấc mộng.","page_number":9,"image":"https://api-vt.umbalena.vn/book/media/?key=eyJhbGciOiJBMjU2S1ciLCJlbmMiOiJBMjU2Q0JDLUhTNTEyIn0.fFn-fFILUcde002dndeg_uEgJ34xonlQes2zdQmyVx-c1KFWU_VwfAHXBIj2M8oRPop8wxPNPpTcznUfFItxFBE-fCg0q7bE.a8ugRXwl6KS_WxDVmAdp8w.orMeEXTK4W8WknkMvlMigZeeUyKaWaWuV9mWiVmKCh1I0zGybKCb2od77wwP_9Ct.tnmOMHgO1jh78JpA7HBJzFo-81AofPGqpB6oI4YizLc","audio":"https://api-vt.umbalena.vn/book/media/?key=eyJhbGciOiJBMjU2S1ciLCJlbmMiOiJBMjU2Q0JDLUhTNTEyIn0.JhppvX0f9fx5mq_359drbcFatygDWLIrfDbxgSF9PDOWu6sQwh6eoOBcygI2fUZLf9AvmFcihDmjHvQHalvqC8eBrdd_GPSD.7Bbo2-JaBlP5YvY1dlp1yg.M-3De7TZzXySllvC6zuBSQ5938OM61Hfd0CS1RSKzoO3CtsmUdoa4teMc1v42AkJ._6W1igr4gZ6eiYJQCunIGHqFcFkjh0UV4dCjvd5r8Mg","ar_file":null,"ar_audio":null,"timing_mapping":"{\n \"fragments\": [\n  {\n   \"begin\": \"0.000\", \n   \"children\": [], \n   \"end\": \"0.000\", \n   \"id\": \"f000001\", \n   \"language\": \"vie\", \n   \"lines\": [\n    \"\\u1ed2\"\n   ]\n  }, \n  {\n   \"begin\": \"0.000\", \n   \"children\": [], \n   \"end\": \"1.440\", \n   \"id\": \"f000002\", \n   \"language\": \"vie\", \n   \"lines\": [\n    \"chi\\u1ebfc \\u0111\\u00e8n\"\n   ]\n  }, \n  {\n   \"begin\": \"1.440\", \n   \"children\": [], \n   \"end\": \"2.440\", \n   \"id\": \"f000003\", \n   \"language\": \"vie\", \n   \"lines\": [\n    \"ng\\u1ee7\"\n   ]\n  }, \n  {\n   \"begin\": \"2.440\", \n   \"children\": [], \n   \"end\": \"2.440\", \n   \"id\": \"f000004\", \n   \"language\": \"vie\", \n   \"lines\": [\n    \"\"\n   ]\n  }, \n  {\n   \"begin\": \"2.440\", \n   \"children\": [], \n   \"end\": \"3.240\", \n   \"id\": \"f000005\", \n   \"language\": \"vie\", \n   \"lines\": [\n    \"** Lung linh\"\n   ]\n  }, \n  {\n   \"begin\": \"3.240\", \n   \"children\": [], \n   \"end\": \"4.680\", \n   \"id\": \"f000006\", \n   \"language\": \"vie\", \n   \"lines\": [\n    \"\\u00e1nh v\\u00e0ng\"\n   ]\n  }, \n  {\n   \"begin\": \"4.680\", \n   \"children\": [], \n   \"end\": \"5.040\", \n   \"id\": \"f000007\", \n   \"language\": \"vie\", \n   \"lines\": [\n    \"** Cho\"\n   ]\n  }, \n  {\n   \"begin\": \"5.040\", \n   \"children\": [], \n   \"end\": \"5.480\", \n   \"id\": \"f000008\", \n   \"language\": \"vie\", \n   \"lines\": [\n    \"b\\u00e9\"\n   ]\n  }, \n  {\n   \"begin\": \"5.480\", \n   \"children\": [], \n   \"end\": \"6.760\", \n   \"id\": \"f000009\", \n   \"language\": \"vie\", \n   \"lines\": [\n    \"m\\u01a1 m\\u00e0ng\"\n   ]\n  }, \n  {\n   \"begin\": \"6.760\", \n   \"children\": [], \n   \"end\": \"7.800\", \n   \"id\": \"f000010\", \n   \"language\": \"vie\", \n   \"lines\": [\n    \"** Ch\\u00ecm v\\u00e0o\"\n   ]\n  }, \n  {\n   \"begin\": \"7.800\", \n   \"children\": [], \n   \"end\": \"8.560\", \n   \"id\": \"f000011\", \n   \"language\": \"vie\", \n   \"lines\": [\n    \"gi\\u1ea5c m\\u1ed9ng.\"\n   ]\n  }\n ]\n}","created_by":108,"modified_by":109},{"id":5319,"book":455,"layout_book":"large_image","created_date":"03-10-2019 15:39","modified_date":"02-10-2021 05:01","content":"Thật nhiều| bạn tốt\nGiúp bé| ngủ say\nĐể| mỗi| sớm mai\nTràn đầy| năng lượng.","page_number":10,"image":"https://api-vt.umbalena.vn/book/media/?key=eyJhbGciOiJBMjU2S1ciLCJlbmMiOiJBMjU2Q0JDLUhTNTEyIn0.js7kgyr5V1iKyy_L3pSsBNV9_N0Cc-uyXBQMlz87FZ3KsROqEbZMO9UYxA0C3Ovx3MPeIOjOpN-u3yj1We2POAiUu-xAnHIi.Q0LyHz1QTzIl5MEPpUXW1g.6hMeSzQ4W0BQ4JQGsLhg2HtPlEOQGs0yS0QX8DtGluCi8bNgxfvOQQToiXjkE6_PwL6HLNaUjV7hGxzwTtuqew.yp5nocWHItAeGphaUEWUlwpKMbw19y1KQcqKv2csTc4","audio":"https://api-vt.umbalena.vn/book/media/?key=eyJhbGciOiJBMjU2S1ciLCJlbmMiOiJBMjU2Q0JDLUhTNTEyIn0.ynIM54g1VZfVqu8HQjuqAVI_lduyVp5f9M9mrLWibX28quGcPPlxwSivxdmHGt6Crlo4qzWtzs5EoL4k_5FX0WchvmC_2Tb3.26F9rDFXowgOcpmJVDhpxQ.9rI-q2RYNi_DN-JbWodPYxXNUapYAM6bHafldtxK1PTdJMGr02IPtTK1ToFA3O3p.W00kios6DvY8r4lKbEHn3CdYgsoVr-S8evJfFwcMjMs","ar_file":null,"ar_audio":null,"timing_mapping":"{\n \"fragments\": [\n  {\n   \"begin\": \"0.000\", \n   \"children\": [], \n   \"end\": \"1.080\", \n   \"id\": \"f000001\", \n   \"language\": \"vie\", \n   \"lines\": [\n    \"Th\\u1eadt nhi\\u1ec1u\"\n   ]\n  }, \n  {\n   \"begin\": \"1.080\", \n   \"children\": [], \n   \"end\": \"2.440\", \n   \"id\": \"f000002\", \n   \"language\": \"vie\", \n   \"lines\": [\n    \"b\\u1ea1n t\\u1ed1t\"\n   ]\n  }, \n  {\n   \"begin\": \"2.440\", \n   \"children\": [], \n   \"end\": \"3.160\", \n   \"id\": \"f000003\", \n   \"language\": \"vie\", \n   \"lines\": [\n    \"** Gi\\u00fap b\\u00e9\"\n   ]\n  }, \n  {\n   \"begin\": \"3.160\", \n   \"children\": [], \n   \"end\": \"3.880\", \n   \"id\": \"f000004\", \n   \"language\": \"vie\", \n   \"lines\": [\n    \"ng\\u1ee7 say\"\n   ]\n  }, \n  {\n   \"begin\": \"3.880\", \n   \"children\": [], \n   \"end\": \"4.680\", \n   \"id\": \"f000005\", \n   \"language\": \"vie\", \n   \"lines\": [\n    \"** \\u0110\\u1ec3\"\n   ]\n  }, \n  {\n   \"begin\": \"4.680\", \n   \"children\": [], \n   \"end\": \"5.240\", \n   \"id\": \"f000006\", \n   \"language\": \"vie\", \n   \"lines\": [\n    \"m\\u00f4\\u0303i\"\n   ]\n  }, \n  {\n   \"begin\": \"5.240\", \n   \"children\": [], \n   \"end\": \"6.000\", \n   \"id\": \"f000007\", \n   \"language\": \"vie\", \n   \"lines\": [\n    \"s\\u01a1\\u0301m mai\"\n   ]\n  }, \n  {\n   \"begin\": \"6.000\", \n   \"children\": [], \n   \"end\": \"7.480\", \n   \"id\": \"f000008\", \n   \"language\": \"vie\", \n   \"lines\": [\n    \"** Tr\\u00e0n \\u0111\\u1ea7y\"\n   ]\n  }, \n  {\n   \"begin\": \"7.480\", \n   \"children\": [], \n   \"end\": \"8.720\", \n   \"id\": \"f000009\", \n   \"language\": \"vie\", \n   \"lines\": [\n    \"n\\u0103ng l\\u01b0\\u1ee3ng.\"\n   ]\n  }\n ]\n}","created_by":108,"modified_by":109}]}